streamlit_passwordless/__init__.py
streamlit_passwordless/__main__.py
streamlit_passwordless/auth.py
streamlit_passwordless/common.py
streamlit_passwordless/config.py
streamlit_passwordless/exceptions.py
streamlit_passwordless/metadata.py
streamlit_passwordless/models.py
streamlit_passwordless/py.typed
streamlit_passwordless/web.py
streamlit_passwordless/app/__init__.py
streamlit_passwordless/app/config.py
streamlit_passwordless/app/main.py
streamlit_passwordless/app/session_state.py
streamlit_passwordless/app/components/__init__.py
streamlit_passwordless/app/components/admin.py
streamlit_passwordless/app/components/keys.py
streamlit_passwordless/app/controllers/__init__.py
streamlit_passwordless/app/controllers/admin.py
streamlit_passwordless/app/controllers/init.py
streamlit_passwordless/app/controllers/sign_in.py
streamlit_passwordless/app/logic/__init__.py
streamlit_passwordless/app/logic/admin.py
streamlit_passwordless/app/pages/__init__.py
streamlit_passwordless/app/pages/admin.py
streamlit_passwordless/app/pages/init.py
streamlit_passwordless/app/pages/sign_in.py
streamlit_passwordless/app/views/__init__.py
streamlit_passwordless/app/views/admin.py
streamlit_passwordless/app/views/init.py
streamlit_passwordless/app/views/sign_in.py
streamlit_passwordless/bitwarden_passwordless/__init__.py
streamlit_passwordless/bitwarden_passwordless/backend.py
streamlit_passwordless/bitwarden_passwordless/cache.py
streamlit_passwordless/bitwarden_passwordless/frontend.py
streamlit_passwordless/bitwarden_passwordless/frontend/build/bootstrap.min.css
streamlit_passwordless/bitwarden_passwordless/frontend/build/button.css
streamlit_passwordless/bitwarden_passwordless/frontend/build/index.html
streamlit_passwordless/bitwarden_passwordless/frontend/build/assets/index-CMHGhxuu.js
streamlit_passwordless/bitwarden_passwordless/frontend/build/assets/index-DDW3kUin.css
streamlit_passwordless/cli/__init__.py
streamlit_passwordless/cli/main.py
streamlit_passwordless-0.18.0.dist-info/licenses/LICENSE
streamlit_passwordless-0.18.0.dist-info/METADATA
streamlit_passwordless-0.18.0.dist-info/WHEEL
streamlit_passwordless-0.18.0.dist-info/entry_points.txt
streamlit_passwordless-0.18.0.dist-info/top_level.txt
streamlit_passwordless-0.18.0.dist-info/RECORD
