Metadata-Version: 2.4
Name: streamlit-passwordless
Version: 0.18.0
Summary: A user model for Streamlit applications based on passwordless technology.
Author-email: Anton Lydell <anton.thedev@tuta.com>
License-Expression: MIT
Project-URL: Bug Tracker, https://github.com/antonlydell/streamlit-passwordless/issues
Project-URL: Documentation, https://github.com/antonlydell/streamlit-passwordless
Project-URL: Source Code, https://github.com/antonlydell/streamlit-passwordless
Keywords: Bitwarden,FIDO2,Passkey,Passwordless,Streamlit,Web,WebAuthn
Classifier: Development Status :: 1 - Planning
Classifier: Environment :: Web Environment
Classifier: Intended Audience :: Developers
Classifier: Intended Audience :: Information Technology
Classifier: Operating System :: OS Independent
Classifier: Programming Language :: Python :: 3 :: Only
Classifier: Programming Language :: Python :: 3.11
Classifier: Programming Language :: Python :: 3.12
Classifier: Programming Language :: Python :: 3.13
Classifier: Programming Language :: Python :: 3.14
Classifier: Programming Language :: JavaScript
Classifier: Topic :: Internet :: WWW/HTTP :: Browsers
Classifier: Topic :: Internet :: WWW/HTTP :: Site Management
Classifier: Topic :: Security
Requires-Python: >=3.11
License-File: LICENSE
Requires-Dist: click>=8.0
Requires-Dist: streamlit>=1.24
Requires-Dist: passwordless>=0.1
Requires-Dist: pydantic>=2.0
Requires-Dist: sqlalchemy>=2.0
Dynamic: license-file
